py8ite/__init__.py
py8ite/py8ite.py
py8ite-1.0.6.dist-info/licenses/LICENSE
py8ite-1.0.6.dist-info/METADATA
py8ite-1.0.6.dist-info/WHEEL
py8ite-1.0.6.dist-info/top_level.txt
py8ite-1.0.6.dist-info/RECORD
