Metadata-Version: 2.4
Name: py8ite
Version: 1.0.6
Summary: The Ultimate Python Utility Function that transforms your Python environment
Home-page: https://github.com/itnovre/py8ite
Author: itnovre
License: MIT
Project-URL: Homepage, https://github.com/itnovre/py8ite
Keywords: utility,development,enhancement,debugging
Classifier: Development Status :: 5 - Production/Stable
Classifier: Intended Audience :: Developers
Classifier: License :: OSI Approved :: MIT License
Classifier: Programming Language :: Python :: 3
Classifier: Programming Language :: Python :: 3.7
Classifier: Programming Language :: Python :: 3.8
Classifier: Programming Language :: Python :: 3.9
Classifier: Programming Language :: Python :: 3.10
Classifier: Programming Language :: Python :: 3.11
Requires-Python: >=3.7
License-File: LICENSE
Dynamic: home-page
Dynamic: license-file
Dynamic: requires-python
